odoo/addons/l10n_br_mis_report/README.rst
odoo/addons/l10n_br_mis_report/__init__.py
odoo/addons/l10n_br_mis_report/__manifest__.py
odoo/addons/l10n_br_mis_report/data/mis_report_bp_generic.xml
odoo/addons/l10n_br_mis_report/data/mis_report_bp_simple.xml
odoo/addons/l10n_br_mis_report/data/mis_report_dre_generic.xml
odoo/addons/l10n_br_mis_report/data/mis_report_dre_simple.xml
odoo/addons/l10n_br_mis_report/data/mis_report_styles.xml
odoo/addons/l10n_br_mis_report/i18n/l10n_br_mis_report.pot
odoo/addons/l10n_br_mis_report/i18n/pt_BR.po
odoo/addons/l10n_br_mis_report/readme/CONFIGURE.md
odoo/addons/l10n_br_mis_report/readme/CONTRIBUTORS.md
odoo/addons/l10n_br_mis_report/readme/DESCRIPTION.md
odoo/addons/l10n_br_mis_report/readme/HISTORY.md
odoo/addons/l10n_br_mis_report/readme/INSTALL.md
odoo/addons/l10n_br_mis_report/readme/ROADMAP.md
odoo/addons/l10n_br_mis_report/readme/USAGE.md
odoo/addons/l10n_br_mis_report/static/description/bp.png
odoo/addons/l10n_br_mis_report/static/description/dre.png
odoo/addons/l10n_br_mis_report/static/description/icon.png
odoo/addons/l10n_br_mis_report/static/description/index.html
odoo_addon_l10n_br_mis_report-17.0.1.0.0.2.dist-info/METADATA
odoo_addon_l10n_br_mis_report-17.0.1.0.0.2.dist-info/WHEEL
odoo_addon_l10n_br_mis_report-17.0.1.0.0.2.dist-info/top_level.txt
odoo_addon_l10n_br_mis_report-17.0.1.0.0.2.dist-info/RECORD
