Metadata-Version: 2.1
Name: odoo-addon-l10n_br_mis_report
Version: 17.0.1.0.0.2
Requires-Python: >=3.10
Requires-Dist: odoo-addon-l10n_br_coa>=17.0dev,<17.1dev
Requires-Dist: odoo-addon-mis_builder>=17.0dev,<17.1dev
Requires-Dist: odoo>=17.0a,<17.1dev
Summary: =?utf-8?q?Templates_de_relat=C3=B3rios_cont=C3=A1beis_brasileiros=3A_Balan=C3=A7o_Patrimonial_e_DRE?=
Home-page: https://github.com/OCA/l10n-brazil
License: AGPL-3
Author: KMEE,Odoo Community Association (OCA)
Author-email: support@odoo-community.org
Classifier: Programming Language :: Python
Classifier: Framework :: Odoo
Classifier: Framework :: Odoo :: 17.0
Classifier: License :: OSI Approved :: GNU Affero General Public License v3
Classifier: Development Status :: 4 - Beta
